bootstrap_navbar/__init__.py
bootstrap_navbar/apps.py
bootstrap_navbar/conftest.py
bootstrap_navbar/manage.py
bootstrap_navbar/navbars/__init__.py
bootstrap_navbar/navbars/base.py
bootstrap_navbar/navbars/bootstrap4.py
bootstrap_navbar/navbars/context_processors.py
bootstrap_navbar/navbars/mixins.py
bootstrap_navbar/templates/bootstrap_navbar/attrs.html
bootstrap_navbar/templates/bootstrap_navbar/bootstrap4/brand.html
bootstrap_navbar/templates/bootstrap_navbar/bootstrap4/dropdown.html
bootstrap_navbar/templates/bootstrap_navbar/bootstrap4/image.html
bootstrap_navbar/templates/bootstrap_navbar/bootstrap4/link.html
bootstrap_navbar/templates/bootstrap_navbar/bootstrap4/list.html
bootstrap_navbar/templates/bootstrap_navbar/bootstrap4/navbar.html
bootstrap_navbar/tests/__init__.py
bootstrap_navbar/tests/test_apps.py
bootstrap_navbar/tests/test_context_processors.py
bootstrap_navbar/tests/test_navbar_mixins.py
bootstrap_navbar/tests/test_navbars_base.py
bootstrap_navbar/tests/test_navbars_bootstrap4.py
django_bootstrap_navbar-0.0.21.dist-info/LICENSE
django_bootstrap_navbar-0.0.21.dist-info/METADATA
django_bootstrap_navbar-0.0.21.dist-info/WHEEL
django_bootstrap_navbar-0.0.21.dist-info/top_level.txt
django_bootstrap_navbar-0.0.21.dist-info/RECORD
