Metadata-Version: 2.1
Name: django-bootstrap-navbar
Version: 0.0.21
Summary: Django navbar package
Home-page: https://gitlab.com/BradleyKirton/django-bootstrap-navbar/
Author: Bradley Stuart Kirton
Author-email: bradleykirton@gmail.com
License: MIT
Keywords: django
Platform: UNKNOWN
Classifier: Development Status :: 4 - Beta
Classifier: Intended Audience :: Developers
Classifier: License :: OSI Approved :: MIT License
Classifier: Programming Language :: Python :: 3.6
Classifier: Operating System :: OS Independent
Classifier: Topic :: Software Development :: Libraries
Classifier: Topic :: Utilities
Classifier: Environment :: Web Environment
Classifier: Framework :: Django
Classifier: Framework :: Django :: 2.1
Provides-Extra: dev
Requires-Dist: django ; extra == 'dev'
Requires-Dist: pytest ; extra == 'dev'
Requires-Dist: pytest-cov ; extra == 'dev'
Requires-Dist: pytest-sugar ; extra == 'dev'
Requires-Dist: django-coverage-plugin ; extra == 'dev'
Requires-Dist: pytest-django ; extra == 'dev'
Requires-Dist: bumpversion ; extra == 'dev'
Requires-Dist: twine ; extra == 'dev'
